setup.py
distributions_pr11/Binomialdistribution.py
distributions_pr11/Gaussiandistribution.py
distributions_pr11/Generaldistribution.py
distributions_pr11/__init__.py
distributions_pr11.egg-info/PKG-INFO
distributions_pr11.egg-info/SOURCES.txt
distributions_pr11.egg-info/dependency_links.txt
distributions_pr11.egg-info/not-zip-safe
distributions_pr11.egg-info/top_level.txt