Metadata-Version: 1.0
Name: distributions-pr11
Version: 0.1
Summary: Gaussian distributions
Home-page: UNKNOWN
Author: mail.prithvi@gmail.com
Author-email: UNKNOWN
License: UNKNOWN
Platform: UNKNOWN
